LICENSE
MANIFEST.in
README.rst
setup.py
django_extras/__init__.py
django_extras/models.py
django_extras.egg-info/PKG-INFO
django_extras.egg-info/SOURCES.txt
django_extras.egg-info/dependency_links.txt
django_extras.egg-info/not-zip-safe
django_extras.egg-info/requires.txt
django_extras.egg-info/top_level.txt
django_extras/contrib/__init__.py
django_extras/contrib/auth/__init__.py
django_extras/contrib/auth/decorators.py
django_extras/contrib/auth/models.py
django_extras/contrib/auth/shortcuts.py
django_extras/core/__init__.py
django_extras/core/types.py
django_extras/core/validators.py
django_extras/db/__init__.py
django_extras/db/models/__init__.py
django_extras/db/models/choices.py
django_extras/db/models/fields/__init__.py
django_extras/db/models/fields/jsonfield.py
django_extras/fixtures/tests.json
django_extras/forms/__init__.py
django_extras/forms/fields.py
django_extras/forms/widgets.py
django_extras/http/__init__.py
django_extras/middleware/__init__.py
django_extras/middleware/timing.py
django_extras/static/.hgleave
django_extras/static/css/jquery/ui.colorPicker.css
django_extras/static/css/jquery/img/blank.gif
django_extras/static/css/jquery/img/colorpicker_background.png
django_extras/static/css/jquery/img/colorpicker_hex.png
django_extras/static/css/jquery/img/colorpicker_hsb_b.png
django_extras/static/css/jquery/img/colorpicker_hsb_h.png
django_extras/static/css/jquery/img/colorpicker_hsb_s.png
django_extras/static/css/jquery/img/colorpicker_indic.gif
django_extras/static/css/jquery/img/colorpicker_overlay.png
django_extras/static/css/jquery/img/colorpicker_rgb_b.png
django_extras/static/css/jquery/img/colorpicker_rgb_g.png
django_extras/static/css/jquery/img/colorpicker_rgb_r.png
django_extras/static/css/jquery/img/colorpicker_select.gif
django_extras/static/css/jquery/img/colorpicker_submit.png
django_extras/static/css/jquery/img/custom_background.png
django_extras/static/css/jquery/img/custom_hex.png
django_extras/static/css/jquery/img/custom_hsb_b.png
django_extras/static/css/jquery/img/custom_hsb_h.png
django_extras/static/css/jquery/img/custom_hsb_s.png
django_extras/static/css/jquery/img/custom_indic.gif
django_extras/static/css/jquery/img/custom_rgb_b.png
